MANIFEST.in
setup.py
Products/__init__.py
Products/__init__.pyc
Products.SilvaKupu.egg-info/PKG-INFO
Products.SilvaKupu.egg-info/SOURCES.txt
Products.SilvaKupu.egg-info/dependency_links.txt
Products.SilvaKupu.egg-info/namespace_packages.txt
Products.SilvaKupu.egg-info/not-zip-safe
Products.SilvaKupu.egg-info/requires.txt
Products.SilvaKupu.egg-info/top_level.txt
Products/kupu/Makefile
Products/kupu/__init__.py
Products/kupu/dist.kupu
Products/kupu/include.kupu
Products/kupu/kupu-i18nextract-sa-diff.patch
Products/kupu/kupu_icon.gif
Products/kupu/make.xsl
Products/kupu/version.txt
Products/kupu/common/fulldoc.html
Products/kupu/common/kupu-pox.cgi
Products/kupu/common/kupu.cgi
Products/kupu/common/kupu.pox
Products/kupu/common/kupu.pox.jspx
Products/kupu/common/kupubasetools.js
Products/kupu/common/kupubeforeunload.js
Products/kupu/common/kupublank.html
Products/kupu/common/kupucleanupexpressions.js
Products/kupu/common/kupucnftable.js
Products/kupu/common/kupucontentfilters.js
Products/kupu/common/kupucontentstyles.css
Products/kupu/common/kupucontextmenu.js
Products/kupu/common/kupudrawers.js
Products/kupu/common/kupudrawerstyles.css
Products/kupu/common/kupueditor.js
Products/kupu/common/kupuhelpers.js
Products/kupu/common/kupuinit.js
Products/kupu/common/kupuinit_experimental.js
Products/kupu/common/kupuinit_form.js
Products/kupu/common/kupuinit_genericelements.js
Products/kupu/common/kupuinit_multi.js
Products/kupu/common/kupuinspector.js
Products/kupu/common/kupuloggers.js
Products/kupu/common/kupumultieditor.js
Products/kupu/common/kupunoi18n.js
Products/kupu/common/kupusaveonpart.js
Products/kupu/common/kupusourceedit.js
Products/kupu/common/kupuspellchecker.js
Products/kupu/common/kupustart.js
Products/kupu/common/kupustart_form.js
Products/kupu/common/kupustart_multi.js
Products/kupu/common/kupustyles.css
Products/kupu/common/kuputoolcollapser.js
Products/kupu/common/sarissa.js
Products/kupu/common/sarissa_ieemu_xpath.js
Products/kupu/common/spellcheck.cgi
Products/kupu/common/kupudrawers/.objects
Products/kupu/common/kupudrawers/allimages.xml
Products/kupu/common/kupudrawers/drawer.xsl
Products/kupu/common/kupudrawers/drawer.xsl.metadata
Products/kupu/common/kupudrawers/imagelibrary.xml
Products/kupu/common/kupudrawers/kupubuttons.xml
