Metadata-Version: 1.1
Name: Products.SilvaKupu
Version: 1.4.2
Summary: Kupu WYSIWYG text editor for Silva 2
Home-page: https://github.com/silvacms/Products.SilvaKupu
Author: Infrae
Author-email: info@infrae.com
License: Kupu License
Keywords: kupu silva zope2
Platform: UNKNOWN
Classifier: Programming Language :: Python
Classifier: Topic :: Software Development :: Libraries :: Python Modules
Classifier: Topic :: Text Editors
